{"mode":"arcade","variant":"neon-rush","coordinates":"x advances to the right; y increases downward.","phase":"dead","level":{"index":0,"number":1,"name":"STARFALL","difficulty":"easy","length":4400},"player":{"x":1164,"y":320,"vy":16.76,"onGround":false,"jumpBuffer":0,"coyoteFrames":0,"airJumpsUsed":1,"airJumpsLeft":0},"score":17,"best":17,"attempt":1,"assistScale":1,"progressPct":26,"timerFrames":174,"upcoming":[{"type":"s","dx":16,"y":330,"w":40,"h":40},{"type":"s","dx":56,"y":330,"w":40,"h":40},{"type":"s","dx":296,"y":330,"w":40,"h":40}]}